{
  "db_name": "MySQL",
  "query": "\nSELECT\n    m.token as `token: tokens::tokens::media_files::MediaFileToken`,\n\n    m.media_type as `media_type: enums::by_table::media_files::media_file_type::MediaFileType`,\n\n    m.maybe_creator_user_token as `maybe_creator_user_token: tokens::tokens::users::UserToken`,\n    m.creator_set_visibility as `creator_set_visibility: enums::common::visibility::Visibility`,\n\n    m.file_size_bytes,\n    m.maybe_duration_millis,\n\n    m.public_bucket_directory_hash,\n    m.maybe_public_bucket_prefix,\n    m.maybe_public_bucket_extension\n\nFROM media_files AS m\nWHERE\n    m.token = ?\n        ",
  "describe": {
    "columns": [
      {
        "ordinal": 0,
        "name": "token: tokens::tokens::media_files::MediaFileToken",
        "type_info": {
          "type": "VarString",
          "flags": "NOT_NULL | UNIQUE_KEY | BINARY | NO_DEFAULT_VALUE",
          "char_set": 224,
          "max_size": 128
        }
      },
      {
        "ordinal": 1,
        "name": "media_type: enums::by_table::media_files::media_file_type::MediaFileType",
        "type_info": {
          "type": "VarString",
          "flags": "NOT_NULL | MULTIPLE_KEY | BINARY | NO_DEFAULT_VALUE",
          "char_set": 224,
          "max_size": 64
        }
      },
      {
        "ordinal": 2,
        "name": "maybe_creator_user_token: tokens::tokens::users::UserToken",
        "type_info": {
          "type": "VarString",
          "flags": "MULTIPLE_KEY | BINARY",
          "char_set": 224,
          "max_size": 128
        }
      },
      {
        "ordinal": 3,
        "name": "creator_set_visibility: enums::common::visibility::Visibility",
        "type_info": {
          "type": "String",
          "flags": "NOT_NULL | BINARY | ENUM",
          "char_set": 224,
          "max_size": 28
        }
      },
      {
        "ordinal": 4,
        "name": "file_size_bytes",
        "type_info": {
          "type": "Long",
          "flags": "NOT_NULL",
          "char_set": 63,
          "max_size": 10
        }
      },
      {
        "ordinal": 5,
        "name": "maybe_duration_millis",
        "type_info": {
          "type": "Long",
          "flags": "",
          "char_set": 63,
          "max_size": 10
        }
      },
      {
        "ordinal": 6,
        "name": "public_bucket_directory_hash",
        "type_info": {
          "type": "VarString",
          "flags": "NOT_NULL | BINARY | NO_DEFAULT_VALUE",
          "char_set": 224,
          "max_size": 128
        }
      },
      {
        "ordinal": 7,
        "name": "maybe_public_bucket_prefix",
        "type_info": {
          "type": "VarString",
          "flags": "BINARY",
          "char_set": 224,
          "max_size": 64
        }
      },
      {
        "ordinal": 8,
        "name": "maybe_public_bucket_extension",
        "type_info": {
          "type": "VarString",
          "flags": "BINARY",
          "char_set": 224,
          "max_size": 64
        }
      }
    ],
    "parameters": {
      "Right": 1
    },
    "nullable": [
      false,
      false,
      true,
      false,
      false,
      true,
      false,
      true,
      true
    ]
  },
  "hash": "8deae5674403372e52eeaf29cb23fe92e562832530eab1e5c7684a10e35c5f36"
}
